[{"id_wisata":"26","id_kategori":"5","lat":"-8.1799995","lng":"122.7691571","wisata":"Danau Asmara - Danau Waibelen","keterangan":"Danau Waibelen","alamat":"Waibao, Tj. Bunga, Kabupaten Flores Timur, Nusa Tenggara Timur","pic":"59538-wisata-hits-danau-asmara-flores-timur-ntt.png"},{"id_wisata":"27","id_kategori":"4","lat":"-8.3430601","lng":"122.971984","wisata":"Taman Bukit Fatima","keterangan":null,"alamat":"Larantuka, Kabupaten Flores Timur, Nusa Tenggara Timur","pic":"a39e0-wisata-hits-taman-bukit-fatima-flores-timur-ntt.png"},{"id_wisata":"28","id_kategori":"7","lat":"-8.3437647","lng":"122.952436","wisata":"Pelabuhan Larantuka","keterangan":null,"alamat":"Lokea, Larantuka, Kabupaten Flores Timur, Nusa Tenggara Timur","pic":"2349f-pemandangan-cantik-di-pelabuhan-larantuka-flores-timur-ntt.png"},{"id_wisata":"29","id_kategori":"7","lat":"-8.3292032","lng":"122.9115149","wisata":"Pemandian Waiplatin","keterangan":null,"alamat":"Mokantarak, Larantuka, Kabupaten Flores Timur, Nusa Tenggara Timur","pic":"e3041-wisata-pemandian-air-panas-mokantarak-flores-timur-ntt.png"},{"id_wisata":"30","id_kategori":"5","lat":"-8.3147219","lng":"122.9584674","wisata":"Gunung Ile Mandiri","keterangan":null,"alamat":"Lewohala, Ile Mandiri, Kabupaten Flores Timur, Nusa Tenggara Timur","pic":"1549f-wisata-hits-gunung-ile-mandiri-flores-timur-ntt.png"},{"id_wisata":"31","id_kategori":"4","lat":"-8.3338884","lng":"122.9939595","wisata":"Masjid Agung Syuhada Flores Timur","keterangan":null,"alamat":"Ekasapta, Larantuka, Kabupaten Flores Timur, Nusa Tenggara Timur","pic":"7a3a3-syuhada.jpg"},{"id_wisata":"32","id_kategori":"3","lat":"-8.316130","lng":"122.988390","wisata":"Golden Cafe & Bistro Larantuka","keterangan":"Golden Cafe & Bistro Larantuka","alamat":"Weri, RT.001\/RW.001, Sarotari, Larantuka, Kabupaten Flores Timur, Nusa Tenggara Tim.","pic":"3965d-capture.jpg"},{"id_wisata":"33","id_kategori":"6","lat":"-8.316860","lng":"123.008240","wisata":"Masjid Al-Amin Weri","keterangan":"Masjid Al-Amin Weri","alamat":"Weri, Larantuka, East Flores Regency, East Nusa Tenggara","pic":"06404-capture.jpg"}]